{
  "users": [
    {
      "id": 1,
      "userEmail": "123.qq.com",
      "userPassword": "123456"
    },
    {
      "id": 2,
      "userEmail": "test.test.com",
      "userPassword": "123456"
    },
    {
      "id": 3,
      "userEmail": "email.qq.com",
      "userPassword": "123456"
    },
    {
      "userEmail": "test@163.com",
      "userPassword": "123123",
      "id": 4
    },
    {
      "userEmail": "Barke@qq.com",
      "userPassword": "123456",
      "id": 5
    },
    {
      "userEmail": "balabala@qq.com",
      "userPassword": "123456",
      "id": 6
    },
    {
      "userEmail": "bbb@qq.com",
      "userPassword": "111",
      "id": 7
    },
    {
      "userEmail": "aaa@qq.ocm",
      "userPassword": "111",
      "id": 8
    },
    {
      "userEmail": "asda@163.com",
      "userPassword": "111",
      "id": 9
    },
    {
      "userEmail": "qwe@qq.com",
      "userPassword": "123",
      "id": 10
    },
    {
      "userEmail": "sds@88.com",
      "userPassword": "123",
      "id": 11
    },
    {
      "userEmail": "123@qq.com",
      "userPassword": "123",
      "id": 12
    },
    {
      "userEmail": "123@qq.com",
      "userPassword": "123",
      "id": 13
    },
    {
      "userEmail": "bsad@qq.com",
      "userPassword": "123",
      "id": 14
    },
    {
      "userEmail": "ccc@qq.com",
      "userPassword": "123456",
      "id": 15
    },
    {
      "userEmail": "aaa@qq.com",
      "userPassword": "123456",
      "isLogin": true,
      "id": 16
    }
  ],
  "menus": [
    {
      "id": 4,
      "good_name": "茄子豆角",
      "good_info": "紫菜，鸡蛋",
      "good_imgSrc": "",
      "good_newPrice": 2,
      "good_oldPrice": 4
    },
    {
      "good_name": "紫菜蛋汤",
      "good_info": "紫菜，鸡蛋",
      "good_imgSrc": "",
      "good_newPrice": 1.5,
      "good_oldPrice": 4,
      "id": 5
    },
    {
      "good_name": "海带排骨汤",
      "good_newPrice": 7.8,
      "good_oldPrice": 13.5,
      "good_info": "海带，排骨高汤",
      "good_imgSrc": "",
      "id": 8
    },
    {
      "good_name": "剁辣椒芽白",
      "good_newPrice": 8.8,
      "good_oldPrice": "9",
      "good_info": "微辣，白菜",
      "id": 9
    },
    {
      "good_name": "干豆角蒸肉",
      "good_newPrice": 13.4,
      "good_oldPrice": 16.4,
      "good_info": "豆角，五花肉",
      "id": 10
    }
  ],
  "orders": [
    {
      "id": 1,
      "name": "Apple",
      "description": "Apple is good!"
    },
    {
      "tiem": "2020-4-26",
      "total_price": 20,
      "order_detail": [
        {
          "good_name": "茄子豆角",
          "quantity": 1
        },
        {
          "good_name": "紫菜蛋汤",
          "quantity": 2
        },
        {
          "good_name": "海带排骨汤",
          "quantity": 3
        }
      ],
      "id": 2
    },
    {
      "time": "2021-04-26T08:31:03.636Z",
      "total_price": 33.5,
      "order_detail": [
        {
          "goodName": "茄子豆角",
          "goodPrice": 2,
          "quantity": 1
        },
        {
          "goodName": "紫菜蛋汤",
          "goodPrice": 1.5,
          "quantity": 1
        },
        {
          "goodName": "海带排骨汤",
          "goodPrice": "7.8",
          "quantity": 1
        },
        {
          "goodName": "剁辣椒芽白",
          "goodPrice": "8.8",
          "quantity": 1
        },
        {
          "goodName": "干豆角蒸肉",
          "goodPrice": "13.4",
          "quantity": 1
        }
      ],
      "id": 3
    },
    {
      "time": "2021-04-26T08:32:09.100Z",
      "total_price": 8.5,
      "order_detail": [
        {
          "goodName": "茄子豆角",
          "goodPrice": 2,
          "quantity": 2
        },
        {
          "goodName": "紫菜蛋汤",
          "goodPrice": 1.5,
          "quantity": 3
        }
      ],
      "id": 4
    },
    {
      "time": "2021/4/26下午4:39:57",
      "total_price": 20.6,
      "order_detail": [
        {
          "goodName": "茄子豆角",
          "goodPrice": 2,
          "quantity": 1
        },
        {
          "goodName": "紫菜蛋汤",
          "goodPrice": 1.5,
          "quantity": 2
        },
        {
          "goodName": "海带排骨汤",
          "goodPrice": "7.8",
          "quantity": 2
        }
      ],
      "id": 5
    },
    {
      "time": "2021/4/26下午7:03:17",
      "total_price": 21.1,
      "order_detail": [
        {
          "goodName": "茄子豆角",
          "goodPrice": 2,
          "quantity": 2
        },
        {
          "goodName": "紫菜蛋汤",
          "goodPrice": 1.5,
          "quantity": 1
        },
        {
          "goodName": "海带排骨汤",
          "goodPrice": "7.8",
          "quantity": 2
        }
      ],
      "order_status": false,
      "id": 6
    }
  ]
}